erlang
tests
