Metadata-Version: 1.0
Name: python-erlang
Version: 0.2.2
Summary: Telecom calculation library for python
Home-page: http://github.com/natemara/python-erlang
Author: Nate Mara
Author-email: natemara@gmail.com
License: MIT
Platform: UNKNOWN
